{
  "todayStats": {
    "total": 17,
    "positive": 1,
    "negative": 1,
    "neutral": 15
  },
  "allTimeStats": {
    "total": 510,
    "positive": 136,
    "negative": 21,
    "neutral": 353,
    "avg_score": 0.6
  },
  "trend": [
    {
      "date": "2026-03-23",
      "total": 28,
      "positive": 0,
      "negative": 0,
      "neutral": 28,
      "avg_score": 0.5
    },
    {
      "date": "2026-03-25",
      "total": 237,
      "positive": 118,
      "negative": 16,
      "neutral": 45,
      "avg_score": 0.74
    },
    {
      "date": "2026-03-26",
      "total": 18,
      "positive": 0,
      "negative": 0,
      "neutral": 18,
      "avg_score": 0.5
    },
    {
      "date": "2026-03-27",
      "total": 10,
      "positive": 0,
      "negative": 0,
      "neutral": 10,
      "avg_score": 0.5
    },
    {
      "date": "2026-03-28",
      "total": 15,
      "positive": 0,
      "negative": 0,
      "neutral": 15,
      "avg_score": 0.5
    },
    {
      "date": "2026-03-30",
      "total": 18,
      "positive": 0,
      "negative": 0,
      "neutral": 18,
      "avg_score": 0.5
    },
    {
      "date": "2026-03-31",
      "total": 14,
      "positive": 0,
      "negative": 0,
      "neutral": 14,
      "avg_score": 0.5
    },
    {
      "date": "2026-04-01",
      "total": 15,
      "positive": 0,
      "negative": 0,
      "neutral": 15,
      "avg_score": 0.5
    },
    {
      "date": "2026-04-02",
      "total": 14,
      "positive": 0,
      "negative": 0,
      "neutral": 14,
      "avg_score": 0.5
    },
    {
      "date": "2026-04-03",
      "total": 17,
      "positive": 1,
      "negative": 1,
      "neutral": 15,
      "avg_score": 0.51
    }
  ],
  "recentArticles": [
    {
      "id": 780,
      "title": "MGK Shares Cute Pics of Baby Saga Blade on Daughter’s First Birthday - Billboard",
      "link": "https://www.billboard.com/music/rock/mgk-cute-pics-baby-saga-blade-daughter-first-birthday-1236213206/",
      "source": "Tavily (www.billboard.com)",
      "snippet": "# MGK Shares Cute Pics of Baby Saga Blade on Daughter’s First Birthday. MGK is sharing pics from his infant daughter Saga Blade’s first birthday celebration. The “Cliché” singer posted a series of snaps of his second-born little one on Wednesday (April 1), obscuring the face of the child he shares with ex actress Megan Fox in a photo carousel of images from the baby’s first year. Elsewhere, MGK (born Colson Baker), 35, and Saga ride a mini-train at what looks like a carnival, take a daddy-daughter nap, dress up for Halloween as Jack Skellington and a little monster, swing on swings and celebrate Christmas with Casie in matching holiday onesies. News*, a day earlier during an Instagram Live, MGK revealed the cute nickname he has for Saga when he said “Hi, princess,” asking the little one if she wanted to “jam” with him.",
      "published_at": "Thu, 02 Apr 2026 11:57:10 GMT",
      "collected_at": "2026-04-03 05:56:34",
      "sentiment": "中性",
      "sentiment_score": 0.5,
      "summary": "此新聞資訊關於饒舌歌手MGK慶祝女兒一歲生日並分享可愛照片，與周杰倫無關。",
      "category": "其他",
      "analyzed": 1
    },
    {
      "id": 781,
      "title": "Jaafar Jackson says memories of uncle Michael Jackson are 'wonderful' - USA Today",
      "link": "https://www.usatoday.com/story/entertainment/celebrities/2026/04/02/jaafar-jackson-remembers-uncle-michael-jackson/89440607007/",
      "source": "Tavily (www.usatoday.com)",
      "snippet": "Jaafar Jackson was just 12 when Michael Jackson died in 2009, but the Hollywood newcomer can still recall the \"wonderful times\" he had with his superstar uncle. In his first TV interview ahead of the release of the Antoine Fuqua biopic \"Michael\" on April 24, in which Jaafar plays Jackson, the 29-year-old actor on April 2 briefly reminisced about his childhood on \"Today with Jenna & Sheinelle.\". ## Katherine Jackson 'couldn't tell if it was me or Michael': Jaafar Jackson. Jaafar – the second youngest son of Jermaine Jackson, Michael's brother and former Jackson 5 member – told the hosts that he's received \"heartwarming\" support from his father and the rest of his family, including grandmother Katherine Jackson. The 95-year-old Jackson family matriarch saw the film and \"said how excellent I did and how much I embodied Michael,\" Jaafar shared. \"Michael\" is releasing against the backdrop of ongoing legal battles between Jackson's sexual assault accusers and his estate.",
      "published_at": "Fri, 03 Apr 2026 00:04:00 GMT",
      "collected_at": "2026-04-03 05:56:34",
      "sentiment": "正面",
      "sentiment_score": 0.75,
      "summary": "Jaafar Jackson在首次電視採訪中分享了與已故叔叔Michael Jackson的美好回憶，並透露家人對他飾演Michael Jackson的傳記電影給予了溫馨支持。",
      "category": "其他",
      "analyzed": 1
    },
    {
      "id": 782,
      "title": "Album Premiere: Gardenia – ‘Self-Titled’ - New Noise Magazine",
      "link": "https://newnoisemagazine.com/premieres/album-premiere-gardenia-self-titled/",
      "source": "Tavily (newnoisemagazine.com)",
      "snippet": "# Album Premiere: Gardenia – ‘Self-Titled’. Gardenia are sharing their new self-titled full-length record, which deals with absence, the subtle ways intimacy erodes under fame and media, and the constant signal overload of modern life. The album was co-produced by Grammy-nominated producer Jack Shirley and the band themselves. The record reflects New York’s evolving heavy indie movement. Listen to the album here:. Gardenia was formed by born-and-bred New Yorkers, singer/bassist Ryan Zakin and drummer Tamir Malik. The duo met each other while working in a Manhattan recording studio. The new record proves how strong their musical bond is, and they aim to continue it for the upcoming days. *Photo courtesy of Michelle Lobianco*. ###### Stay Connected. ###### Subscribe. ### New Noise Print Subscription. Subscribe to receive physical monthly issues in the mail! This website uses cookies to ensure you get the best experience on our website.",
      "published_at": "Fri, 27 Mar 2026 14:53:19 GMT",
      "collected_at": "2026-04-03 05:56:34",
      "sentiment": "中性",
      "sentiment_score": 0.5,
      "summary": "此新聞報導關於樂團Gardenia的新專輯發布，與周杰倫無關。",
      "category": "其他",
      "analyzed": 1
    },
    {
      "id": 783,
      "title": "Publishing Briefs: Bastian Langebaek Signs with Sony Music Publishing UK - Billboard",
      "link": "https://www.billboard.com/lists/publishing-briefs-bastian-langebaek-sony-music-publishing/",
      "source": "Tavily (www.billboard.com)",
      "snippet": "**Sony Music Publishing UK**, in partnership with its JV partner **Second Songs**, signed a global publishing agreement with Copenhagen-based songwriter **Bastian Langebaek**, which includes future works. “I’m incredibly excited and grateful to sign a new publishing deal with Second Songs & Sony Music Publishing, getting to work once more with [Second Songs co-founder] **Mark Gale**, who I first signed with 11 years ago, a moment that changed everything,” said Langebaek in a statement. “Lykke Li is a generational talent who has consistently pushed the boundaries of pop music, not just in the Nordics but on the global stage,” **Lars Karlsson**, managing director of Warner Chappell Music Scandinavia, said in a statement. “We couldn’t be more excited to welcome Julianna Rankin into the Sony Music Publishing family alongside Big Loud Texas,” added **Anna Weisband**, senior vp, creative A&R, Sony Music Publishing Nashville. “Aya is a remarkable artist of rare sensitivity whose music has resonated around the world for nearly 10 years, reaching several generations,” **Matthieu Tessier,** managing director of Warner Chappell Music France, said in a statement.",
      "published_at": "Thu, 02 Apr 2026 19:49:12 GMT",
      "collected_at": "2026-04-03 05:56:34",
      "sentiment": "中性",
      "sentiment_score": 0.5,
      "summary": "此新聞報導主要關於Sony Music Publishing UK簽約Bastian Langebaek等音樂出版協議，與周杰倫無直接關聯。",
      "category": "其他",
      "analyzed": 1
    },
    {
      "id": 784,
      "title": "LeBron on Luka's injury: 'We'll see what happens' - ESPN",
      "link": "https://www.espn.com/watch/player/_/id/48383149",
      "source": "Tavily (www.espn.com)",
      "snippet": "## Calgary Flames vs. ## Nashville Predators vs. ## Adelaide United vs. ESPN+ • Australian A-League Women. ESPN2 • RE-AIR • NCAA Men's Basketball. ACCN • RE-AIR • All ACC. ## SEC Now. SECN • RE-AIR • SEC Now. ESPNU • RE-AIR • NCAA Men's Basketball. ESPNews • RE-AIR • X Games. ESPN Deportes • ES • Futbol Picante Noche. ## Jordan Lawlar crushes 1st MLB HR for D-backs. ## Jack Hughes tallies second goal vs. ## Jordan Eberle scores 41 seconds in for Kraken. ## Paul Skenes 'fired up' for Konnor Griffin's MLB debut. ## Chris Webber: I trust Illinois, but it'll be a slugfest vs. ## Calgary Flames vs. ## Nashville Predators vs. ## Adelaide United vs. ESPN+ • Australian A-League Women. ESPN2 • RE-AIR • NCAA Men's Basketball. ACCN • RE-AIR • All ACC. ESPNU • RE-AIR • NCAA Men's Basketball. ESPNews • RE-AIR • X Games. ESPN Deportes • ES • Futbol Picante Noche. * Your US State Privacy Rights.",
      "published_at": "Fri, 03 Apr 2026 05:42:51 GMT",
      "collected_at": "2026-04-03 05:56:34",
      "sentiment": "中性",
      "sentiment_score": 0.5,
      "summary": "這則新聞內容主要關於各項體育賽事（如NBA、NHL、NCAA等）的報導與摘要，與周杰倫無關。",
      "category": "其他",
      "analyzed": 1
    },
    {
      "id": 785,
      "title": "Why President Trump Fired Pam Bondi; Americans Drown in Medical Debt | April 2 - Modern Ghana",
      "link": "https://www.modernghana.com/amp/videonews/632014",
      "source": "Tavily (www.modernghana.com)",
      "snippet": "# Why President Trump Fired Pam Bondi; Americans Drown in Medical Debt | April 2. Sources close to President Donald Trump told NBC News that he felt she had bungled the Epstein files saga and hadn't done enough to prosecute the president's political enemies. NBC News senior Capitol Hill correspondent Garrett Haake breaks down how she has changed the Justice Department — and whether interim AG Todd Blanche will stay on permanently. Plus, the rising cost of medical care is drowning Americans in debt. In the latest edition of NBC News' “Unaffordable America” series, senior financial reporter Gretchen Morgenson explains how the problem is expected to worsen as more than 10 million Americans lose health care coverage as a result of the president's signature “big, beautiful bill.”. “Here's the Scoop” is an evening podcast from NBC News. https://www.youtube.com/@HeresTheScoop. See more exclusive reporting at our NBC News YouTube channel:. Apple: https://podcasts.apple.com/us/podcast/heres-the-scoop/id1820996352. Spotify: https://open.spotify.com/show/2gXjYWGzbOiONamY4rY4xI. Amazon Music: https://music.amazon.com/podcasts/901a073c-bd6f-4726-ab4d-acefc00ec15e/here's-the-scoop? asc\\_campaign=&asc\\_refurl=https%3A%2F%2Fwww.nbcnews.com%2Fheres-the-scoop-daily-podcast&asc\\_source=https%3A%2F%2Fwww.nbcnews.com%2F\\_desktop. iHeart: https://www.iheart.com/podcast/552-the-drink-with-kate-snow-317749113/. Pandora: https://www.pandora.com/podcast/the-drink-with-kate-snow/PC:1001112945. TuneIn: https://tunein.com/podcasts/News/The-Drink-with-Kate-Snow-p4704762/?",
      "published_at": "Fri, 03 Apr 2026 04:00:00 GMT",
      "collected_at": "2026-04-03 05:56:34",
      "sentiment": "中性",
      "sentiment_score": 0.5,
      "summary": "此新聞報導主要關於美國政治、前總統川普解僱Pam Bondi的原因，以及美國民眾面臨的醫療債務問題，內容與周杰倫無關。",
      "category": "其他",
      "analyzed": 1
    },
    {
      "id": 786,
      "title": "Rutgers Scarlet Knights vs. Creighton Bluejays The Crown Highlights 🏀 FOX College Hoops - FOX Sports",
      "link": "https://www.foxsports.com/watch/fmc-xy42fi3iwzj69tyz",
      "source": "Tavily (www.foxsports.com)",
      "snippet": "# Rutgers Scarlet Knights vs. Creighton Bluejays The Crown Highlights 🏀 FOX College Hoops. ## Check out the best moments between the Rutgers Scarlet Knights and the Creighton Bluejays in The Crown Quarterfinals! College Basketball  CBK - Rutgers Scarlet Knights vs. Creighton Bluejays - 04/02/2026  Rutgers Scarlet Knights  Creighton Bluejays. ### Fedor Žugić throws FULL COURT baseline pass to Josh Dix for slam dunk, sealing Creighton win over Rutgers. West Virginia Mountaineers The Crown Highlights 🏀 FOX College Hoops. ### Tariq Francis lobs it UP to Lino Mark, extending Rutgers' lead over Creighton. ### Stanford's Ebuka Okorie throws down dunk, extending lead over West Virginia. ### West Virginia's DJ Thomas throws down slam dunk, extending lead over Stanford. ### Baylor Bears vs. Minnesota Golden Gophers The Crown Highlights 🏀 FOX College Hoops. ### Obi Agbim throws halfcourt lob to Cameron Carr for STRONG slam dunk, extending Baylor's lead over Minnesota. Colorado Buffaloes The Crown Highlights 🏀 FOX College Hoops.",
      "published_at": "Fri, 03 Apr 2026 05:34:01 GMT",
      "collected_at": "2026-04-03 05:56:34",
      "sentiment": "中性",
      "sentiment_score": 0.5,
      "summary": "此新聞內容為大學籃球賽事精華，與周杰倫無關。",
      "category": "其他",
      "analyzed": 1
    },
    {
      "id": 787,
      "title": "Long Island man had enough drugs to kill 2 million people, officials say - NBC New York",
      "link": "https://www.nbcnewyork.com/video/news/long-island-man-had-enough-drugs-to-kill-2-million-people-officials-say/6485176/?amp=1",
      "source": "Tavily (www.nbcnewyork.com)",
      "snippet": "# Long Island man had enough drugs to kill 2 million people, officials say. A 42-year-old man was indicted, accused of trafficking drugs in Suffolk County. ## Local. #### Adrienne Bailon-Houghton on purpose, family and her new film ‘Chef's Kiss'. #### Man declared innocent 47 years after high-profile killing of NYC rabbi. #### Police shoot, kill man while serving arrest warrant in the Bronx. #### Huge fire tears through homes and businesses in Butler. #### Heart-broken grandmother speaks after 7-month-old girl shot and killed. NEWSLETTERS   WATCH NBC NEW YORK NEWS 24/7   SEND A VIDEO OR PHOTO TO NBC NY   LOCAL NEWS   WEATHER   WEATHER ALERTS   SCHOOL CLOSINGS   U.S. & WORLD NEWS   VIDEO   INVESTIGATIONS   BETTER GET BAQUERO   SUBMIT A TIP   TV LISTINGS / NBC SCHEDULE   ENTERTAINMENT   NEW YORK LIVE   1ST LOOK   GEORGE TO THE RESCUE   OPEN HOUSE   SPORTS   COMMUNITY. Submit Tips to Better Get Baquero   Submit Photos and Video   Contests   Newsletters   TV Schedule   Our Apps   Cozi TV   Our News Standards.",
      "published_at": "Thu, 02 Apr 2026 23:57:13 GMT",
      "collected_at": "2026-04-03 05:56:34",
      "sentiment": "中性",
      "sentiment_score": 0.5,
      "summary": "此新聞報導主要關於長島一名男子因販毒被起訴，以及其他多則地方新聞，與周杰倫無直接關聯。",
      "category": "其他",
      "analyzed": 1
    },
    {
      "id": 788,
      "title": "Ja Morant Personal Announcement Reignites Miami Trade Rumors - Newsweek",
      "link": "https://www.newsweek.com/sports/nba/ja-morant-personal-announcement-reignites-miami-trade-rumors-11778735",
      "source": "Tavily (www.newsweek.com)",
      "snippet": "# Ja Morant Personal Announcement Reignites Miami Trade Rumors. Once again, Ja Morant finds himself fueling the fire of what feels like an inevitable move away from Memphis. The Memphis Grizzlies star guard has reportedly listed his Memphis home for $3.5 million, a move that immediately rekindles questions about his long-term future with the franchise. And this latest personal decision only makes the idea of Morant playing in a Grizzlies jersey next season feel even more unbelievable. Back in December, Morant was listed as an executor of a trust that purchased a $3.2 million home in Miami-Dade County. That purchase came just weeks before the Feb. 5 trade deadline, when Morant’s name surfaced in league-wide discussions but ultimately remained in Memphis. The trade package sent Morant to Miami in exchange for veteran forward Andrew Wiggins and fifth-year guard Davion Mitchell. At this point, it feels like a lot less like \"is Morant getting traded\" and simply more of when. ## Donald Trump Gets Bad News Minutes After Iran War Speech.",
      "published_at": "Fri, 03 Apr 2026 05:45:00 GMT",
      "collected_at": "2026-04-03 05:56:34",
      "sentiment": "中性",
      "sentiment_score": 0.5,
      "summary": "此新聞主要報導籃球員Ja Morant的交易傳聞，與周杰倫無關。",
      "category": "其他",
      "analyzed": 1
    },
    {
      "id": 789,
      "title": "A Letter Of Forgiveness To My Neighbor, Who Went On TV To Mock My Faith - huffpost.com",
      "link": "https://www.huffpost.com/entry/alabama-attorney-general-candidate-anti-islam_n_69ce7637e4b0332f12c1d035",
      "source": "Tavily (www.huffpost.com)",
      "snippet": "\"Jay, your campaign ad did not sound like justice. Why do we never attach the word “radical” to Christianity, Judaism, Hinduism, or Buddhism — or to any faith that humans manipulate to justify violence? My truest religion is love — the central message of all faiths. “Perhaps the better question is not who created whom, but why humans feel compelled to imagine the divine at all.”. Jay, your campaign ad did not sound like justice. When you say, “Allahu Akbar your butt back to the Middle East,” you are not speaking to extremists. I hope this letter opens your heart, Jay. This letter of forgiveness — of love and of the same humanity that we share. I hope it allows you to see this humanity in a Muslim father, neighbor and citizen who loves this country and this state fiercely. And I hope you leave with this: my Islam, my heart, my life, is a testimony of peace, love and forgiveness — far from anything you call “radical.”.",
      "published_at": "Thu, 02 Apr 2026 17:12:58 GMT",
      "collected_at": "2026-04-03 05:56:34",
      "sentiment": "負面",
      "sentiment_score": 0.4,
      "summary": "一封來自鄰居的公開信，批評一位名為「Jay」的人物在競選廣告中關於信仰與種族的爭議言論，同時表達寬恕與愛。",
      "category": "爭議",
      "analyzed": 1
    },
    {
      "id": 790,
      "title": "'I'm Not the Most Strict': Jay Cutler Says You're Overthinking Your Form – and Missing Out on Muscle - menshealth.com",
      "link": "https://www.menshealth.com/uk/building-muscle/a70904372/jay-cutler-perfect-form-build-muscle/",
      "source": "Tavily (www.menshealth.com)",
      "snippet": "2. 'I'm Not the Most Strict': Jay Cutler Says You're Overthinking Your Form – and Missing Out on Muscle. # 'I'm Not the Most Strict': Jay Cutler Says You're Overthinking Your Form – and Missing Out on Muscle. Bodybuilding legend Jay Cutler doesn’t buy into the idea that perfect form is always necessary to build muscle. Cutler still focuses on ‘feeling’ each rep and staying in control, but doesn’t shy away from using a little momentum to challenge his muscles – as seen in his approach to barbell curls. 'I’m not the most strict when I do my curls,' Cutler says in a YouTube video. Remember, I was throwing around crazy weights, and I always feel my movements. When curling, Cutler uses a slight swing at the bottom of the movement to help initiate the lift, but he doesn’t let momentum take over. Using a small amount of momentum allows him to handle heavier weights while still maintaining control, ensuring the key parts of the lift remain effective.",
      "published_at": "Wed, 01 Apr 2026 12:56:00 GMT",
      "collected_at": "2026-04-03 05:56:34",
      "sentiment": "中性",
      "sentiment_score": 0.5,
      "summary": "此新聞報導關於健身傳奇人物Jay Cutler的訓練哲學，與周杰倫無關。",
      "category": "其他",
      "analyzed": 1
    },
    {
      "id": 791,
      "title": "\"It's not like no one was there in the auction\" - Aakash Chopra highlights CSK's 3 wrong decisions ahead of IPL 2026 clash vs PBKS - Sportskeeda",
      "link": "https://www.sportskeeda.com/cricket/news-it-s-like-one-auction-aakash-chopra-highlights-csk-s-3-wrong-decisions-ahead-ipl-2026-clash-vs-pbks",
      "source": "Tavily (www.sportskeeda.com)",
      "snippet": "Your login session has expired. Please logout and login again. * SA-W vs NZ-W. * AUS-W vs WI-W. Ahead of the Chennai Super Kings' (CSK) IPL 2026 clash against the Punjab Kings (PBKS), former India player Aakash Chopra has highlighted three wrong decisions taken by the Chennai-based franchise. He pointed out that the five-time champions have picked only two overseas batters, with Matthew Short not even being an ideal cover for Dewald Brevis, despite the presence of multiple other options in the auction. > \"They are the only team that has only two overseas batters. He should have also been a middle-order batter. Matthew Short's numbers while batting at No. 4 are absolutely ordinary. You have taken a player who won't be available for you till April 21 or 24,\" he said. The cricketer-turned-commentator added that Johnson is also not an ideal replacement for Ellis as he is not a death bowler.",
      "published_at": "Fri, 03 Apr 2026 05:37:43 GMT",
      "collected_at": "2026-04-03 05:56:34",
      "sentiment": "中性",
      "sentiment_score": 0.5,
      "summary": "此新聞內容與周杰倫無關，主要討論板球隊伍Chennai Super Kings在IPL 2026賽季前的選人決策失誤。",
      "category": "其他",
      "analyzed": 1
    },
    {
      "id": 792,
      "title": "Dan Hurley takes UConn to 3 Of last 4 Final Fours Stream of General Videos - CBS Sports",
      "link": "https://www.cbssports.com/watch/general/video/sportshq-network-13001",
      "source": "Tavily (www.cbssports.com)",
      "snippet": "# Dan Hurley takes UConn to 3 Of last 4 Final Fours. ## Dan Hurley takes UConn to 3 Of last 4 Final Fours. ### CBS Sports Golazo Network. #### UEFA Women's Champions League Today. ### UEFA Champions League Channel. #### Kylian Mbappe's Best Goals in the Champions League. ### UFC. ### CBS Sports HQ. #### Scoreboard Final. ### CBS Sports Network. #### 2026 Tournament Rebound - Second Round: Utah State vs. #### Sheffield United vs. #### West Bromwich Albion vs. ## UFC News & Highlights. #### UFC Fighter Breakdown: Renato Moicano vs Chris Duncan. ### UFC. #### HIGHLIGHTS & REACTIONS From UFC Fight Night On Paramount +. ### UFC. #### Joe Pyfer Previews Adesanya Fight, Talks Faith Shift. ### UFC. #### Maycee Barber Previews Grasso Fight, Touts Ferocity. ### UFC. ### UFC. #### HIGHLIGHTS & REACTIONS From UFC Fight Night On Paramount+. ### UFC. #### UFC Fight Night Preview: Movsar Evloev Vs. Lerone Murphy. ### UFC. #### Michael 'Venom' Page Previews Sam Patterson Fight.",
      "published_at": "Fri, 03 Apr 2026 04:51:42 GMT",
      "collected_at": "2026-04-03 05:56:34",
      "sentiment": "中性",
      "sentiment_score": 0.5,
      "summary": "這則新聞內容主要關於體育賽事與選手，與周杰倫無關。",
      "category": "其他",
      "analyzed": 1
    },
    {
      "id": 793,
      "title": "Chicago Bulls vs Milwaukee Bucks Nov 7, 2025 Box Scores - NBA",
      "link": "https://www.nba.com/game/chi-vs-mil-0022500035/box-score?utm_source=ko_1nymu710kbxfc9d44&utm_campaign=nba_onramp&utm_medium=social_partner_widget&utm_term=NBA&utm_content=0022500035&partnerRef=NBA&howToWatch=false&cp1=Threads&cp2=Post&cp3=%7Bcp_3%7D&cp4=%7Bcp_4%7D&referrer=utm_source%3Dko_1nymu710kbxfc9d44%26utm_campaign%3D%7Bcampaign_id%7D%26utm_medium%3DNBA%26utm_term%3D%7BpartnerRef%7D%26utm_content%3D%7Bgame_id%7D",
      "source": "Tavily (www.nba.com)",
      "snippet": "Emirates NBA Cup: East Group C. # Giannis' 41 powers Bucks. Vučević C | 31:12 | 7 | 13 | 53.8 | 2 | 3 | 66.7 | 0 | 0 | 0.0 | 0 | 6 | 6 | 1 | 1 | 0 | 2 | 3 | 16 | -11 |. ## Milwaukee Bucks. Antetokounmpo F | 37:17 | 16 | 32 | 50.0 | 1 | 3 | 33.3 | 8 | 11 | 72.7 | 4 | 11 | 15 | 9 | 2 | 2 | 4 | 1 | 41 | 16 |. Turner C | 31:19 | 8 | 14 | 57.1 | 5 | 8 | 62.5 | 2 | 3 | 66.7 | 3 | 5 | 8 | 0 | 4 | 1 | 2 | 4 | 23 | 19 |. Antetokounmpo | DNP - Coach's Decision | | | | | | | | | | | | | | | | | | | |.",
      "published_at": "Fri, 03 Apr 2026 04:08:35 GMT",
      "collected_at": "2026-04-03 05:56:34",
      "sentiment": "中性",
      "sentiment_score": 0.5,
      "summary": "這則新聞報導的是一場NBA比賽的數據，與周杰倫無關。",
      "category": "其他",
      "analyzed": 1
    },
    {
      "id": 794,
      "title": "Spurs roll past the Clippers 118-99 without Victor Wembanyama for 11th straight win - Greenwich Time",
      "link": "https://www.greenwichtime.com/sports/article/spurs-roll-past-the-clippers-118-99-without-22186995.php",
      "source": "Tavily (www.greenwichtime.com)",
      "snippet": "# Spurs roll past the Clippers 118-99 without Victor Wembanyama for 11th straight win. (AP) — De'Aaron Fox scored 22 points on 9-of-13 shooting, and the San Antonio Spurs beat the Los Angeles Clippers 118-99 on Thursday night without Victor Wembanyama in the lineup to win their 11th in a row. The Spurs had six players in double figures, including Stephon Castle with 20 points and Dylan Harper with 19 off the bench. Kawhi Leonard scored 24 points to lead the Clippers with his 53rd consecutive game of 20 or more points. This was the second straight year Madden Orlovsky's drawings were displayed on the ESPN show. The Spurs led by 26 points in the first half. This CT park is nominated for USA Today's list of the top 10 best city parks. CT’s best garden centers to visit this winter. CT retirement communities are lovely places to call home. Treat yourself to a day of luxury at the best spas in CT.",
      "published_at": "Fri, 03 Apr 2026 05:12:46 GMT",
      "collected_at": "2026-04-03 05:56:34",
      "sentiment": "中性",
      "sentiment_score": 0.5,
      "summary": "此新聞報導主要關於馬刺隊在沒有Victor Wembanyama的情況下擊敗快艇隊，內容與周杰倫無關。",
      "category": "其他",
      "analyzed": 1
    },
    {
      "id": 795,
      "title": "Jack White, Arlo Parks, Anne Hathaway & More: New Music Friday Guide - Billboard",
      "link": "https://www.billboard.com/music/pop/jack-white-arlo-parks-anne-hathaway-new-music-friday-guide-1236213934/",
      "source": "Tavily (www.billboard.com)",
      "snippet": "# Jack White, Arlo Parks, Anne Hathaway & More: New Music Friday Guide. Billboard’s Friday Music Guide serves as a handy guide to New Music Friday’s most essential releases each week — the key music that everyone will be talking about today, and that will be dominating playlists this weekend and beyond. This week, Jack White prepares for his gig on *Saturday Night Live* with a punchy two-pack, Arlo Parks shares her gorgeous third album, *Ambiguous Desire*, and Anne Hathaway — ahem, Mother Mary — continues teasing her upcoming role as an iconic pop star in the A24 film of the same name… plus much more. Released as a surprise two-pack alongside single “Derecho Demonico,” it’s possible these could be the two songs Jack White will perform as musical guest on *Saturday Night Live* come April 4. “Time” comes as the latest single from Sofia D’Angelo — perhaps better known as a member of New York indie-pop collective MICHELLE — who in 2024 started releasing solo material again for the first time in four years.",
      "published_at": "Fri, 03 Apr 2026 05:22:19 GMT",
      "collected_at": "2026-04-03 05:56:34",
      "sentiment": "中性",
      "sentiment_score": 0.5,
      "summary": "此篇Billboard新音樂指南主要介紹Jack White、Arlo Parks和Anne Hathaway等藝人的新作品，內容未提及周杰倫。",
      "category": "其他",
      "analyzed": 1
    },
    {
      "id": 796,
      "title": "K-pop hits dominate the soundtrack of 'XO, Kitty' Season 3 with some familiar songs from the 'To All the Boys I've Loved Before' films featuring too. Read more below. - facebook.com",
      "link": "https://www.facebook.com/deadline/posts/k-pop-hits-dominate-the-soundtrack-of-xo-kitty-season-3-with-some-familiar-songs/1301702898496714/",
      "source": "Tavily (www.facebook.com)",
      "snippet": "# K-pop hits dominate the soundtrack of... ## Deadline Hollywood's Post. ### **Deadline Hollywood**. K-pop hits dominate the soundtrack of 'XO, Kitty' Season 3 with some familiar songs from the 'To All the Boys I've Loved Before' films featuring too. Image 1: 'XO, Kitty' Season 3 Soundtrack: From Fletcher To Ashe To SEVENTEEN. Image 5: 'XO, Kitty' Season 3 Soundtrack: From Fletcher To Ashe To SEVENTEEN. 'XO, Kitty' Season 3 Soundtrack: From Fletcher To Ashe To SEVENTEEN. ### 'XO, Kitty' Season 3 Soundtrack: From Fletcher To Ashe To SEVENTEEN. Image 9: 'XO, Kitty' Season 3 Soundtrack: From Fletcher To Ashe To SEVENTEEN. 'XO, Kitty' Season 3 Soundtrack: From Fletcher To Ashe To SEVENTEEN. ### 'XO, Kitty' Season 3 Soundtrack: From Fletcher To Ashe To SEVENTEEN.",
      "published_at": "Thu, 02 Apr 2026 14:00:32 GMT",
      "collected_at": "2026-04-03 05:56:34",
      "sentiment": "中性",
      "sentiment_score": 0.5,
      "summary": "此新聞報導主要關於影集《XO, Kitty》第三季的配樂，內容提及K-pop及其他藝人，但未提及周杰倫。",
      "category": "其他",
      "analyzed": 1
    },
    {
      "id": 766,
      "title": "Why Michael Jackson’s daughter, Paris, won’t stop ‘til she gets enough from his estate - The Conversation",
      "link": "https://theconversation.com/why-michael-jacksons-daughter-paris-wont-stop-til-she-gets-enough-from-his-estate-279510",
      "source": "Tavily (theconversation.com)",
      "snippet": "She is asking a court to take a closer look at how the pop icon’s estate is being handled by its executors – the people responsible for managing it. Paris Jackson has accused executors John Branca and John McClain of paying themselves and the estate’s lawyers too much, and for leaving $464 million owned by the estate uninvested. Paris Jackson has also stated that the $150 million film is a “botched production.” The executors have responded by arguing that the application of their expertise to other productions about the singer has already provided a huge payoff to the estate. The executors also recently won a court battle against Paris Jackson that ended with a judge ordering her to pay their attorney’s fees in a related dispute. Like other executors in this situation, the men handling Jackson’s estate have hired lawyers, accountants and other professionals to assist them. In this case, Paris Jackson is complaining that the compensation paid to executors of her father’s estate has been excessive.",
      "published_at": "Wed, 01 Apr 2026 12:48:16 GMT",
      "collected_at": "2026-04-02 05:56:50",
      "sentiment": "中性",
      "sentiment_score": 0.5,
      "summary": "此新聞內容關於麥可傑克森女兒對其遺產處理方式的爭議，與周杰倫無直接關聯。",
      "category": "其他",
      "analyzed": 1
    },
    {
      "id": 767,
      "title": "MGK Celebrates Daughter Saga Blade's First Birthday with Never-Before-Seen Photos from the Last Year - Yahoo News New Zealand",
      "link": "https://nz.news.yahoo.com/mgk-celebrates-daughter-saga-blades-202602210.html",
      "source": "Tavily (nz.news.yahoo.com)",
      "snippet": "# MGK Celebrates Daughter Saga Blade's First Birthday with Never-Before-Seen Photos from the Last Year. * MGK shared a heartfelt Instagram tribute for his daughter Saga Blade's first birthday with photos and videos from the past year. * Saga is MGK's second daughter and his first child with ex-fiancée Megan Fox. The rapper and girl dad, 35, is marking his daughter Saga Blade's first birthday with a special tribute to her on Instagram. The post featured a compilation of photos and videos of him and his little girl, whom he welcomed with ex Megan Fox last March. \"1 🧁❤️‍🔥,\" the doting dad simply captioned his post for his baby girl, which also included sweet snaps with his older daughter, Casie, 16, whom he shares with his ex Emma Cannon. MGK first announced the exciting news that he welcomed his second daughter, his first with Fox, on his Instagram. MGK, whose real name is Colson Baker, started off the video showing off some special time with his daughter Saga,.",
      "published_at": "Wed, 01 Apr 2026 20:26:02 GMT",
      "collected_at": "2026-04-02 05:56:50",
      "sentiment": "中性",
      "sentiment_score": 0.5,
      "summary": "此新聞報導美國藝人MGK慶祝女兒生日，與周杰倫無直接關聯。",
      "category": "其他",
      "analyzed": 1
    },
    {
      "id": 768,
      "title": "Kanye West Surpasses J. Cole Thanks To “BULLY” Streaming Success - hotnewhiphop.com",
      "link": "https://www.hotnewhiphop.com/986566-kanye-west-j-cole-streaming",
      "source": "Tavily (www.hotnewhiphop.com)",
      "snippet": "# Kanye West Surpasses J. Jul 26, 2015; Toronto, Ontario, CAN; Recording artist Kanye West performs during the closing ceremony for the 2015 Pan Am Games at Pan Am Ceremonies Venue. Over the weekend, Kanye West dropped his long-awaited twelfth studio album, earning mixed reactions from listeners. Over the weekend, Kanye West dropped his long-awaited twelfth studio album, *BULLY.* While the project has earned mixed reviews from listeners, it was quick to become a commercial success. ## Kanye West Wireless Festival. Kanye West and his 100-member Sunday Service Choir performed along with West's pastor, Adam Tyson. Music   Kanye West Finally Settles “Vultures 1” Sample Dispute. Music   Kanye West Makes Bizarre Comparison Between Nazism And Bisexuality. Numbers   Kanye West's \"Bully\" Receives Astronomical First Week Sales Projections. Music   Kanye West Suffers Major Loss Amid Legal Battle Over $57 Million Mansion. * music   Kanye West's \"Bully\" Gets Completely Ripped Apart By Pitchfork, And Fans Can't Stop Coping.",
      "published_at": "Tue, 31 Mar 2026 16:55:53 GMT",
      "collected_at": "2026-04-02 05:56:50",
      "sentiment": "中性",
      "sentiment_score": 0.5,
      "summary": "這則新聞主要報導肯伊威斯特新專輯《BULLY》的商業成功與評價，與周杰倫無關。",
      "category": "其他",
      "analyzed": 1
    },
    {
      "id": 769,
      "title": "Howie Mandel doubles down on awkward apology to Kelly Ripa, Mark Consuelos: 'I look great' - ew.com",
      "link": "https://ew.com/howie-mandel-apology-mark-consuelos-kelly-ripa-11940564",
      "source": "Tavily (ew.com)",
      "snippet": "# Howie Mandel doubles down on awkward semi-apology after snapping at Mark Consuelos, Kelly Ripa on air. Mandel said it's \"up to you to discern\" whether or not his apology video was genuine, after he snapped at Ripa and Consuelos on \"Live With Kelly and Mark.\". Howie Mandel has doubled down on his awkward semi-apology to Kelly Ripa and Mark Consuelos, after the *America's Got Talent* host and comedian snapped at the cohosting couple live on the air. Days after sharing an Instagram video in which he partially apologized for scolding on television the *Live With Kelly and Mark* stars for praising his looks at age 70, Mandel added another layer of confusion to the ordeal in his answer to a podcaster's inquiry on the matter. In the comments section of Mandel's original apology video, longtime *Live* producer Michael Gelman shared his thoughts as he wrote, \"During these divided times, one thing we can all agree upon is that you do look great ...For your age.\".",
      "published_at": "Wed, 01 Apr 2026 17:59:17 GMT",
      "collected_at": "2026-04-02 05:56:50",
      "sentiment": "中性",
      "sentiment_score": 0.5,
      "summary": "此新聞報導關於Howie Mandel對Kelly Ripa和Mark Consuelos的尷尬半道歉，與周杰倫無直接關聯。",
      "category": "其他",
      "analyzed": 1
    },
    {
      "id": 770,
      "title": "NFL star Nacua in rehab, says attorney - Yahoo Sports",
      "link": "https://sports.yahoo.com/articles/nfl-star-nacua-enters-rehab-025042066.html",
      "source": "Tavily (sports.yahoo.com)",
      "snippet": "# NFL star Nacua in rehab, says attorney. Los Angeles Rams wide receiver Puka Nacua has checked himself into rehab, his attorney said Wednesday. The Rams star \"voluntarily entered a private facility to focus on his health, personal growth, and overall development,\" lawyer Levi McCathern told AFP in a statement. Nacua topped the NFL with 129 receptions last season, adding a total of 1,715 yards, as the Rams reached the NFC Championship game before losing to eventual Super Bowl winners Seattle. Last month, a Jewish woman filed a lawsuit against Nacua alleging that he made an antisemitic statement and later bit her during a night out in Los Angeles on New Year's Eve. His lawyer said Nacua denies the allegation of antisemitism, calling it a \"blatant lie,\" and describing the bite as \"horseplay.\". Nacua's decision to enter rehab was prior to and unrelated to the lawsuit, said the attorney.",
      "published_at": "Thu, 02 Apr 2026 04:06:00 GMT",
      "collected_at": "2026-04-02 05:56:50",
      "sentiment": "中性",
      "sentiment_score": 0.5,
      "summary": "此新聞關於NFL球星Puka Nacua因個人健康問題進入復健中心，並面臨一宗反猶太言論及咬人指控的訴訟，內容未提及周杰倫。",
      "category": "其他",
      "analyzed": 1
    },
    {
      "id": 771,
      "title": "Seeing Steph Curry is a reminder Warriors have plenty left to play for - San Francisco Chronicle",
      "link": "https://www.sfchronicle.com/sports/annkillion/article/seeing-steph-curry-reminder-warriors-plenty-left-22184683.php",
      "source": "Tavily (www.sfchronicle.com)",
      "snippet": "# Seeing Steph Curry is a reminder Warriors have plenty left to play for. ## In a season marred by injuries, the Golden State Warriors still have stakes to play for with Stephen Curry on the mend and some ambitions for this season and next to realize and sustain. Curry hadn’t shot on the floor before a game — with the whole world watching — since the last game he played, January 30th, sixty days earlier. If Curry returns Sunday, the Warriors would have five regular-season games remaining to try to get organized for a play-in game on either April 14 or April 15. There was some hope — certainly from ESPN — that Curry could play in the nationally televised game on Wednesday night. Seeing Steph Curry is a reminder Warriors have plenty left to play for. In a season marred by injuries, the Golden State Warriors still have stakes to play for with Stephen Curry on the mend and some ambitions for this season and next to realize and sustain.",
      "published_at": "Thu, 02 Apr 2026 05:42:57 GMT",
      "collected_at": "2026-04-02 05:56:50",
      "sentiment": "中性",
      "sentiment_score": 0.5,
      "summary": "此新聞內容與周杰倫無關，主要報導史蒂芬·柯瑞回歸及金州勇士隊的賽季展望。",
      "category": "其他",
      "analyzed": 1
    },
    {
      "id": 772,
      "title": "Puka Nacua: Los Angeles Rams wide receiver went to rehab before being sued by a woman for assault and battery, attorney says - Sky Sports",
      "link": "https://www.skysports.com/nfl/news/12118/13527078/puka-nacua-los-angeles-rams-wide-receiver-went-to-rehab-before-being-sued-by-a-woman-for-assault-and-battery-attorney-says",
      "source": "Tavily (www.skysports.com)",
      "snippet": "+ Sky Sports with no contract. # Puka Nacua: Los Angeles Rams wide receiver went to rehab before being sued by a woman for assault and battery, attorney says. Puka Nacua is currently in a rehabilitation facility, according to his attorney Levi McCathern; Nacua was last month sued for assault and battery by a woman over allegations he made an antisemitic statement and bit her on New Year's Eve. Thursday 2 April 2026 06:45, UK. Los Angeles Rams All-Pro wide receiver Puka Nacua is in rehab and was there before he was sued for assault and battery by a woman who says he made an antisemitic statement and bit her on the shoulder on New Year's Eve, according to his attorney. Plaintiff Madison Atiabi and her attorney, Joseph Kar, claim Nacua made an antisemitic exclamation that emotionally distressed her when they were together on New Year's Eve. She says Nacua bit her and left teeth marks on her shoulder when they were in a van together later in the night, and she claims Nacua also bit her friend's thumb. ## Around Sky. + Sky Sports with no contract.",
      "published_at": "Thu, 02 Apr 2026 05:47:04 GMT",
      "collected_at": "2026-04-02 05:56:50",
      "sentiment": "中性",
      "sentiment_score": 0.5,
      "summary": "此新聞資訊與周杰倫無關，主要報導洛杉磯公羊隊寬接手Puka Nacua因被控襲擊和毆打而進入康復中心。",
      "category": "其他",
      "analyzed": 1
    },
    {
      "id": 773,
      "title": "‘The Bachelorette’ Star Konrad Bien-Stephen Dead at 35 - Variety Australia",
      "link": "https://au.variety.com/2026/tv/news/konrad-bien-stephen-34861/",
      "source": "Tavily (au.variety.com)",
      "snippet": "# ‘The Bachelorette’ Star Konrad Bien-Stephen Dead at 35. Australian reality star Konrad Bien-Stephen has passed away at the age of 35. Bien-Stephen’s management confirmed the news in a statement this morning (April 2). It’s understood that Bien-Stephen passed away on Monday night (March 30) in Melbourne. No other details have been forthcoming at the time of writing. “It is with deep sadness that we share the news of the passing of Konrad Bien-Stephen,” the statement said. “We ask that you respect the privacy of their family during this incredibly difficult time. Bien-Stephen first rose to national fame as a contestant on Brooke Blurton’s season of “The Bachelorette” in 2021. Bien-Stephen famously dated fellow reality TV personality Abbie Chatfield from November 2021 to August 2022. Bien-Stephen’s last Instagram post came just six days ago, showing him on a job site. ## Love Film & TV? “The Amazing Race” contestant Luke O’Halloran said, “Love ya mate x.”.",
      "published_at": "Thu, 02 Apr 2026 01:42:57 GMT",
      "collected_at": "2026-04-02 05:56:50",
      "sentiment": "中性",
      "sentiment_score": 0.5,
      "summary": "澳洲實境秀明星Konrad Bien-Stephen於35歲逝世，死因未詳，此資訊與周杰倫無直接關聯。",
      "category": "其他",
      "analyzed": 1
    },
    {
      "id": 774,
      "title": "\"RCB might be thinking that he was with them for ₹1 crore\" - Aakash Chopra lauds DC bowler's spell in IPL 2026 clash vs LSG - Sportskeeda",
      "link": "https://www.sportskeeda.com/cricket/news-rcb-might-thinking-1-crore-aakash-chopra-lauds-dc-bowler-s-spell-ipl-2026-clash-vs-lsg",
      "source": "Tavily (www.sportskeeda.com)",
      "snippet": "Your login session has expired. Please logout and login again. * SA-W vs NZ-W. * AUS-W vs WI-W. * \"RCB might be thinking that he was with them for ₹1 crore\" - Aakash Chopra lauds DC bowler's spell in IPL 2026 clash vs LSG. Former India player Aakash Chopra has lauded Lungi Ngidi for bowling a potent spell in the Delhi Capitals' (DC) IPL 2026 clash against the Lucknow Super Giants (LSG). In a video shared on his YouTube channel, 'Aakash Chopra,' the former India batter praised T Natarajan and Ngidi for picking up three wickets apiece in Wednesday's game, reckoning RCB might be regretting releasing the Proteas seamer. He also knew that Axar Patel would come to bowl because he is a good matchup against Mitchell Marsh and Aiden Markram. **Get real-time updates on** **IPL 2025****, live scores,** **IPL Prediction****,** **match schedule****,** **points table**,**Result** **& squad -****CSK****,** **MI****,** **RCB****,** **KKR****,** **SRH****,** **LSG****,** **DC****,** **GT**, **PBKS**.",
      "published_at": "Thu, 02 Apr 2026 05:35:35 GMT",
      "collected_at": "2026-04-02 05:56:50",
      "sentiment": "中性",
      "sentiment_score": 0.5,
      "summary": "這則新聞與周杰倫無關，內容主要報導印度板球超級聯賽（IPL）的賽事分析。",
      "category": "其他",
      "analyzed": 1
    },
    {
      "id": 775,
      "title": "Thursday news quiz: daring dogs, delinquent capybaras and far too many bananas - The Guardian",
      "link": "https://www.theguardian.com/lifeandstyle/2026/apr/02/the-guardian-thursday-quiz-general-knowledge-topical-news-trivia-241",
      "source": "Tavily (www.theguardian.com)",
      "snippet": "# Thursday news quiz: daring dogs, delinquent capybaras and far too many bananas. Test yourself on topical news trivia, pop culture and general knowledge every Thursday. It is time for the Thursday news quiz, where, thanks to our illustration from Anaïs Mims, you must decide whether you are gliding serenely across the waters of knowledge, your elegant neck forming a perfect question mark, or paddling furiously beneath the surface, one wrong answer away from an undignified flap. Fifteen questions on topical headlines, pop culture and general knowledge await. There are no prizes, but we always enjoy hearing how you got on in the comments. **The Thursday news quiz, No 241**. *If you really do think there has been an egregious error in one of the questions or answers – and can show your working and are absolutely 100% positive you aren’t attempting to factcheck a joke – you can complain about it in the comments below. ## Comments(…).",
      "published_at": "Thu, 02 Apr 2026 05:00:17 GMT",
      "collected_at": "2026-04-02 05:56:50",
      "sentiment": "中性",
      "sentiment_score": 0.5,
      "summary": "這則新聞是關於《衛報》的週四新聞問答，內容涵蓋時事、流行文化和常識，與周杰倫無關。",
      "category": "其他",
      "analyzed": 1
    },
    {
      "id": 776,
      "title": "‘Chicago Med’ Boss & Oliver Platt Talk Shocking Charles Ending (VIDEO) - TV Insider",
      "link": "https://www.tvinsider.com/1255493/chicago-med-charles-stroke-is-oliver-platt-leaving/",
      "source": "Tavily (www.tvinsider.com)",
      "snippet": "# ‘Chicago Med’ Boss & Oliver Platt Talk Shocking Charles Ending (VIDEO). There have been quite a few cast changes over the years on *Chicago Med*, but now, in its 11th season, two OGs are still around: Oliver Platt and S. The former gets the spotlight in the Thursday, April 1 episode, “The Book of Charles,” and he’s delivering one of his best performances of the series. “Epatha and I were so traumatized shooting that scene,” Oliver Platt tells TV Insider. “Oliver and I particularly paid close attention to earlier in the season that Charles was having trouble with his medication, and he went to his doctor and tried to see what was going on.”. Watch the full video interview above for more from Oliver Platt and showrunner Allen MacDonald about this shocking development for Charles. * Who Is 'Chicago Med' Star Oliver Platt's Wife? * 'Chicago Med' Boss & Oliver Platt Preview 'Book of Charles' Episode. ## Chicago Med## Allen MacDonald## Oliver Platt## S.",
      "published_at": "Thu, 02 Apr 2026 01:00:54 GMT",
      "collected_at": "2026-04-02 05:56:50",
      "sentiment": "中性",
      "sentiment_score": 0.5,
      "summary": "此新聞報導主要關於美劇《芝加哥醫情》的劇情發展與演員Oliver Platt的表現，與周杰倫無關。",
      "category": "其他",
      "analyzed": 1
    },
    {
      "id": 777,
      "title": "Wemby drops 41 points, adds 18 rebounds in win vs. Warriors - ESPN",
      "link": "https://www.espn.com/video/clip?id=48374360",
      "source": "Tavily (www.espn.com)",
      "snippet": "# Wemby drops 41 points, adds 18 rebounds in Spurs' win. ### The Latest. ### The Latest. ## Wemby drops 41 points, adds 18 rebounds in Spurs' win. Wemby drops 41 points, adds 18 rebounds in Spurs' win. ## Hawks-Magic get into scuffle after Goga Bitadze's hard foul on Jock Landale. Hawks-Magic get into scuffle after Goga Bitadze's hard foul on Jock Landale. ## Sharks win on Alexander Wennberg's goal with 31 seconds left. Sharks win on Alexander Wennberg's goal with 31 seconds left. ## Denzel Clarke dazzles with HR robbery. ## L.J. Cryer fights off defender for and-1. L.J. Cryer fights off defender for and-1. * ## Wemby stretches over a defender to finish. Wemby stretches over a defender to finish. * Your US State Privacy Rights. * Children's Online Privacy Policy. CALL 1-800-GAMBLER, (800) 327-5050 or visit gamblinghelplinema.org (MA). 888-789-7777/visit ccpg.org (CT), or visit www.mdgamblinghelp.org (MD). 21+ and present in most states. (18+ DC/KY/NH/WY). Void in ONT/OR/NH.",
      "published_at": "Thu, 02 Apr 2026 04:46:40 GMT",
      "collected_at": "2026-04-02 05:56:50",
      "sentiment": "中性",
      "sentiment_score": 0.5,
      "summary": "此新聞內容主要報導美國體育賽事，與周杰倫無直接關聯。",
      "category": "其他",
      "analyzed": 1
    },
    {
      "id": 778,
      "title": "Tom Clancy’s The Division® Resurgence Now Available Worldwide on iOS and Android Devices - Business Wire",
      "link": "https://www.businesswire.com/news/home/20260330606957/en/Tom-Clancys-The-Division-Resurgence-Now-Available-Worldwide-on-iOS-and-Android-Devices",
      "source": "Tavily (www.businesswire.com)",
      "snippet": "SAN FRANCISCO--(BUSINESS WIRE)--Today, Ubisoft announced that Tom Clancy’s The Division Resurgence, a free-to-play third-person RPG shooter mobile game set in a massive urban open world, is now available worldwide\\* on iOS and Android devices. Developed by a team of experts within Ubisoft Mobile Games,\\*\\* The Division Resurgence features a brand-new standalone campaign. SAN FRANCISCO--(BUSINESS WIRE)--Today, Ubisoft® announced that Siege® X, the largest and most transformative update in Tom Clancy’s Rainbow Six Siege’s 10-year history, is now free to access on PlayStation®4, PlayStation®5, the Xbox One family of consoles, Xbox Series X | S, and Windows PC, including on Steam, and Amazon Luna\\*. SAN FRANCISCO--(BUSINESS WIRE)--Today, Ubisoft announced that Tom Clancy’s Rainbow Six Siege® X, the largest and most transformative evolution in the game’s history, will launch as a free update on June 10 on Ubisoft+, Ubisoft’s subscription service\\*, PlayStation®4, PlayStation®5, the Xbox One family of consoles, Xbox Series X | S, Windows PC, including on Steam, and Amazon Luna.",
      "published_at": "Tue, 31 Mar 2026 16:00:00 GMT",
      "collected_at": "2026-04-02 05:56:50",
      "sentiment": "中性",
      "sentiment_score": 0.5,
      "summary": "這則新聞報導了Ubisoft遊戲《全境封鎖：曙光》和《虹彩六號：圍攻行動X》的發布資訊，內容與周杰倫無關。",
      "category": "其他",
      "analyzed": 1
    }
  ],
  "latestReport": {
    "id": 11,
    "report_date": "2026-04-03",
    "total_articles": 17,
    "positive_count": 1,
    "negative_count": 1,
    "neutral_count": 15,
    "daily_summary": "今日搜集到的新聞中，沒有直接關於周杰倫的報導。主要焦點集中在其他娛樂、體育及商業新聞，例如MGK慶祝女兒生日、Jaafar Jackson分享對麥可傑克森的回憶，以及Kanye West專輯的討論等。周杰倫今日未有新的公開活動或重大新聞發布。",
    "key_events": [
      "無周杰倫報導",
      "今日無相關",
      "未有新消息"
    ],
    "created_at": "2026-04-03 05:58:29"
  },
  "recentReports": [
    {
      "id": 11,
      "report_date": "2026-04-03",
      "total_articles": 17,
      "positive_count": 1,
      "negative_count": 1,
      "neutral_count": 15,
      "daily_summary": "今日搜集到的新聞中，沒有直接關於周杰倫的報導。主要焦點集中在其他娛樂、體育及商業新聞，例如MGK慶祝女兒生日、Jaafar Jackson分享對麥可傑克森的回憶，以及Kanye West專輯的討論等。周杰倫今日未有新的公開活動或重大新聞發布。",
      "key_events": [
        "無周杰倫報導",
        "今日無相關",
        "未有新消息"
      ],
      "created_at": "2026-04-03 05:58:29"
    },
    {
      "id": 10,
      "report_date": "2026-04-02",
      "total_articles": 14,
      "positive_count": 0,
      "negative_count": 0,
      "neutral_count": 14,
      "daily_summary": "今日搜集到的新聞內容，經仔細審閱後，並未發現任何與華語天王周杰倫直接相關的報導或動態。所有新聞焦點均集中於國際娛樂圈、體育賽事、政治動態及其他社會議題，周杰倫今日並無公開或被報導的活動。",
      "key_events": [
        "無周杰倫相關新聞",
        "今日無其公開動態",
        "新聞焦點在其他"
      ],
      "created_at": "2026-04-02 05:58:33"
    },
    {
      "id": 9,
      "report_date": "2026-04-01",
      "total_articles": 15,
      "positive_count": 0,
      "negative_count": 0,
      "neutral_count": 15,
      "daily_summary": "根據今日搜集到的新聞列表，並未發現任何與華語樂壇天王周杰倫直接相關的報導。所有提及「Jay」的內容皆指其他公眾人物，因此本日無周杰倫的娛樂新聞焦點事件可供整理與摘要。",
      "key_events": [
        "無周杰倫消息",
        "今日無相關報導",
        "未有焦點事件"
      ],
      "created_at": "2026-04-01 06:19:35"
    },
    {
      "id": 8,
      "report_date": "2026-03-31",
      "total_articles": 14,
      "positive_count": 0,
      "negative_count": 0,
      "neutral_count": 14,
      "daily_summary": "今日所提供的娛樂新聞中，並未包含任何與周杰倫直接相關的報導或動態。所有焦點均集中在其他國際藝人的最新專輯發行、演唱會消息、影視作品續訂、體育賽事結果以及科技產品更新等多元領域。",
      "key_events": [
        "無周杰倫新聞",
        "無相關報導",
        "今日無焦點"
      ],
      "created_at": "2026-03-31 06:07:12"
    },
    {
      "id": 7,
      "report_date": "2026-03-30",
      "total_articles": 18,
      "positive_count": 0,
      "negative_count": 0,
      "neutral_count": 18,
      "daily_summary": "今日新聞摘要中，經仔細審閱所有提供的報導，並未發現任何與華語流行天王周杰倫相關的最新動態或新聞事件。所有提及『Jay-Z』的報導均為不同藝人的資訊，因此今日無周杰倫的焦點事件可供整理與發布。",
      "key_events": [
        "無周杰倫新聞",
        "無相關動態",
        "無焦點事件"
      ],
      "created_at": "2026-03-30 06:28:29"
    },
    {
      "id": 6,
      "report_date": "2026-03-28",
      "total_articles": 15,
      "positive_count": 0,
      "negative_count": 0,
      "neutral_count": 15,
      "daily_summary": "周杰倫近日話題豐富，睽違四年將推新專輯，預告收錄求婚影片，並鬆口巡演最終站可能回台灣。他揭露當年向昆凌求婚的「假古堡」內幕，新歌MV斥資上億引發熱議。此外，他曾設計連川普都擁有的手錶，早期寫歌「罵方文山」也成經典。",
      "key_events": [
        "睽違四年將推新專輯",
        "揭露求婚假古堡內幕",
        "巡演最終站可能回台"
      ],
      "created_at": "2026-03-28 05:37:33"
    },
    {
      "id": 5,
      "report_date": "2026-03-27",
      "total_articles": 10,
      "positive_count": 0,
      "negative_count": 0,
      "neutral_count": 10,
      "daily_summary": "周杰倫今日焦點圍繞新專輯《太陽之子》發行。主打歌MV斥資上億由《阿凡達》團隊打造，專輯中更收錄為小女兒Jacinda創作的《女兒殿下》，並預告將曝光他向昆凌求婚的浪漫影片。他還透露了求婚時的核彈級內幕，以及曾兩度恐慌症發作的經歷。此外，周董也鬆口未來巡演最終站可能回到台灣。",
      "key_events": [
        "新專輯《太陽之子》發行",
        "斥資上億MV與女兒歌",
        "透露求婚內幕與恐慌症"
      ],
      "created_at": "2026-03-27 01:16:54"
    }
  ]
}